[
  {
    "id": 1,
    "title": "Superhost",
    "price": 70574,
    "rating": 70.574,
    "reviews": 0,
    "property_type": "Unknown",
    "city": "Almaty",
    "country": "Kazakhstan",
    "currency": "USD",
    "scraped_at": "2025-12-04T00:19:26.020078",
    "source": "airbnb_kz"
  },
  {
    "id": 1,
    "title": "Guest favorite",
    "price": 94388,
    "rating": 94.388,
    "reviews": 88,
    "property_type": "Unknown",
    "city": "Astana",
    "country": "Kazakhstan",
    "currency": "USD",
    "scraped_at": "2025-12-04T00:19:57.044568",
    "source": "airbnb_kz"
  },
  {
    "id": 1,
    "title": "Guest favorite",
    "price": 101311,
    "rating": 101.311,
    "reviews": 27,
    "property_type": "Unknown",
    "city": "Shymkent",
    "country": "Kazakhstan",
    "currency": "USD",
    "scraped_at": "2025-12-04T00:20:26.490818",
    "source": "airbnb_kz"
  },
  {
    "id": 1,
    "title": "Superhost",
    "price": 113468,
    "rating": 113.468,
    "reviews": 4,
    "property_type": "Unknown",
    "city": "Karaganda",
    "country": "Kazakhstan",
    "currency": "USD",
    "scraped_at": "2025-12-04T00:21:04.411816",
    "source": "airbnb_kz"
  },
  {
    "id": 1,
    "title": "Apartment in Aktobe",
    "price": 75091,
    "rating": 75.091,
    "reviews": 0,
    "property_type": "Apartment",
    "city": "Aktobe",
    "country": "Kazakhstan",
    "currency": "USD",
    "scraped_at": "2025-12-04T00:21:35.320958",
    "source": "airbnb_kz"
  },
  {
    "id": 1,
    "title": "Apartment in Taraz",
    "price": 86838,
    "rating": 86.838,
    "reviews": 0,
    "property_type": "Apartment",
    "city": "Taraz",
    "country": "Kazakhstan",
    "currency": "USD",
    "scraped_at": "2025-12-04T00:22:06.790624",
    "source": "airbnb_kz"
  },
  {
    "id": 1,
    "title": "Guest favorite",
    "price": 95464,
    "rating": 95.464,
    "reviews": 12,
    "property_type": "Unknown",
    "city": "Pavlodar",
    "country": "Kazakhstan",
    "currency": "USD",
    "scraped_at": "2025-12-04T00:22:43.511628",
    "source": "airbnb_kz"
  },
  {
    "id": 2,
    "title": "Apartment in Pavlodar",
    "price": 78154,
    "rating": 78.154,
    "reviews": 4,
    "property_type": "Apartment",
    "city": "Pavlodar",
    "country": "Kazakhstan",
    "currency": "USD",
    "scraped_at": "2025-12-04T00:22:43.531651",
    "source": "airbnb_kz"
  },
  {
    "id": 3,
    "title": "Apartment in Pavlodar",
    "price": 85818,
    "rating": 85.818,
    "reviews": 0,
    "property_type": "Apartment",
    "city": "Pavlodar",
    "country": "Kazakhstan",
    "currency": "USD",
    "scraped_at": "2025-12-04T00:22:43.572121",
    "source": "airbnb_kz"
  },
  {
    "id": 4,
    "title": "Apartment in Pavlodar",
    "price": 133730,
    "rating": 133.73,
    "reviews": 0,
    "property_type": "Apartment",
    "city": "Pavlodar",
    "country": "Kazakhstan",
    "currency": "USD",
    "scraped_at": "2025-12-04T00:22:43.604744",
    "source": "airbnb_kz"
  },
  {
    "id": 5,
    "title": "Apartment in Pavlodar",
    "price": 107100,
    "rating": 107.1,
    "reviews": 0,
    "property_type": "Apartment",
    "city": "Pavlodar",
    "country": "Kazakhstan",
    "currency": "USD",
    "scraped_at": "2025-12-04T00:22:43.639341",
    "source": "airbnb_kz"
  },
  {
    "id": 6,
    "title": "Apartment in Pavlodar",
    "price": 130752,
    "rating": 130.752,
    "reviews": 0,
    "property_type": "Apartment",
    "city": "Pavlodar",
    "country": "Kazakhstan",
    "currency": "USD",
    "scraped_at": "2025-12-04T00:22:43.666439",
    "source": "airbnb_kz"
  },
  {
    "id": 7,
    "title": "Apartment in Pavlodar",
    "price": 119545,
    "rating": 119.545,
    "reviews": 6,
    "property_type": "Apartment",
    "city": "Pavlodar",
    "country": "Kazakhstan",
    "currency": "USD",
    "scraped_at": "2025-12-04T00:22:43.692621",
    "source": "airbnb_kz"
  },
  {
    "id": 8,
    "title": "Apartment in Pavlodar",
    "price": 76996,
    "rating": 76.996,
    "reviews": 0,
    "property_type": "Apartment",
    "city": "Pavlodar",
    "country": "Kazakhstan",
    "currency": "USD",
    "scraped_at": "2025-12-04T00:22:43.748383",
    "source": "airbnb_kz"
  },
  {
    "id": 9,
    "title": "Apartment in Pavlodar",
    "price": 97924,
    "rating": 97.924,
    "reviews": 3,
    "property_type": "Apartment",
    "city": "Pavlodar",
    "country": "Kazakhstan",
    "currency": "USD",
    "scraped_at": "2025-12-04T00:22:43.778691",
    "source": "airbnb_kz"
  },
  {
    "id": 10,
    "title": "Apartment in Pavlodar",
    "price": 179317,
    "rating": 179.317,
    "reviews": 0,
    "property_type": "Apartment",
    "city": "Pavlodar",
    "country": "Kazakhstan",
    "currency": "USD",
    "scraped_at": "2025-12-04T00:22:43.797056",
    "source": "airbnb_kz"
  },
  {
    "id": 11,
    "title": "Apartment in Pavlodar",
    "price": 71303,
    "rating": 71.303,
    "reviews": 4,
    "property_type": "Apartment",
    "city": "Pavlodar",
    "country": "Kazakhstan",
    "currency": "USD",
    "scraped_at": "2025-12-04T00:22:43.816491",
    "source": "airbnb_kz"
  },
  {
    "id": 12,
    "title": "Superhost",
    "price": 86838,
    "rating": 86.838,
    "reviews": 4,
    "property_type": "Unknown",
    "city": "Pavlodar",
    "country": "Kazakhstan",
    "currency": "USD",
    "scraped_at": "2025-12-04T00:22:43.836297",
    "source": "airbnb_kz"
  },
  {
    "id": 13,
    "title": "Apartment in Pavlodar",
    "price": 123020,
    "rating": 123.02,
    "reviews": 7,
    "property_type": "Apartment",
    "city": "Pavlodar",
    "country": "Kazakhstan",
    "currency": "USD",
    "scraped_at": "2025-12-04T00:22:43.860037",
    "source": "airbnb_kz"
  },
  {
    "id": 14,
    "title": "Apartment in Pavlodar",
    "price": 107100,
    "rating": 107.1,
    "reviews": 0,
    "property_type": "Apartment",
    "city": "Pavlodar",
    "country": "Kazakhstan",
    "currency": "USD",
    "scraped_at": "2025-12-04T00:22:43.885939",
    "source": "airbnb_kz"
  },
  {
    "id": 15,
    "title": "Superhost",
    "price": 81302,
    "rating": 81.302,
    "reviews": 0,
    "property_type": "Unknown",
    "city": "Pavlodar",
    "country": "Kazakhstan",
    "currency": "USD",
    "scraped_at": "2025-12-04T00:22:43.912476",
    "source": "airbnb_kz"
  },
  {
    "id": 16,
    "title": "Apartment in Pavlodar",
    "price": 101195,
    "rating": 101.195,
    "reviews": 0,
    "property_type": "Apartment",
    "city": "Pavlodar",
    "country": "Kazakhstan",
    "currency": "USD",
    "scraped_at": "2025-12-04T00:22:43.938304",
    "source": "airbnb_kz"
  },
  {
    "id": 17,
    "title": "Apartment in Pavlodar",
    "price": 83943,
    "rating": 83.943,
    "reviews": 0,
    "property_type": "Apartment",
    "city": "Pavlodar",
    "country": "Kazakhstan",
    "currency": "USD",
    "scraped_at": "2025-12-04T00:22:43.963078",
    "source": "airbnb_kz"
  },
  {
    "id": 18,
    "title": "Apartment in Pavlodar",
    "price": 141960,
    "rating": 141.96,
    "reviews": 3,
    "property_type": "Apartment",
    "city": "Pavlodar",
    "country": "Kazakhstan",
    "currency": "USD",
    "scraped_at": "2025-12-04T00:22:43.989416",
    "source": "airbnb_kz"
  },
  {
    "id": 1,
    "title": "Guest favorite",
    "price": 101460,
    "rating": 101.46,
    "reviews": 6,
    "property_type": "Unknown",
    "city": "Ust-Kamenogorsk",
    "country": "Kazakhstan",
    "currency": "USD",
    "scraped_at": "2025-12-04T00:23:16.116707",
    "source": "airbnb_kz"
  },
  {
    "id": 2,
    "title": "Apartment in Ust'-Kamenogorsk",
    "price": 82187,
    "rating": 82.187,
    "reviews": 11,
    "property_type": "Apartment",
    "city": "Ust-Kamenogorsk",
    "country": "Kazakhstan",
    "currency": "USD",
    "scraped_at": "2025-12-04T00:23:16.137007",
    "source": "airbnb_kz"
  },
  {
    "id": 3,
    "title": "Apartment in Ust'-Kamenogorsk",
    "price": 91464,
    "rating": 91.464,
    "reviews": 0,
    "property_type": "Apartment",
    "city": "Ust-Kamenogorsk",
    "country": "Kazakhstan",
    "currency": "USD",
    "scraped_at": "2025-12-04T00:23:16.157939",
    "source": "airbnb_kz"
  },
  {
    "id": 4,
    "title": "Superhost",
    "price": 101460,
    "rating": 101.46,
    "reviews": 0,
    "property_type": "Unknown",
    "city": "Ust-Kamenogorsk",
    "country": "Kazakhstan",
    "currency": "USD",
    "scraped_at": "2025-12-04T00:23:16.176880",
    "source": "airbnb_kz"
  },
  {
    "id": 5,
    "title": "Superhost",
    "price": 120737,
    "rating": 120.737,
    "reviews": 0,
    "property_type": "Unknown",
    "city": "Ust-Kamenogorsk",
    "country": "Kazakhstan",
    "currency": "USD",
    "scraped_at": "2025-12-04T00:23:16.195982",
    "source": "airbnb_kz"
  },
  {
    "id": 6,
    "title": "Apartment in Ust'-Kamenogorsk",
    "price": 105579,
    "rating": 1.5,
    "reviews": 0,
    "property_type": "Apartment",
    "city": "Ust-Kamenogorsk",
    "country": "Kazakhstan",
    "currency": "USD",
    "scraped_at": "2025-12-04T00:23:16.216934",
    "source": "airbnb_kz"
  },
  {
    "id": 7,
    "title": "Apartment in Ust'-Kamenogorsk",
    "price": 109994,
    "rating": 109.994,
    "reviews": 0,
    "property_type": "Apartment",
    "city": "Ust-Kamenogorsk",
    "country": "Kazakhstan",
    "currency": "USD",
    "scraped_at": "2025-12-04T00:23:16.235567",
    "source": "airbnb_kz"
  },
  {
    "id": 8,
    "title": "Superhost",
    "price": 171467,
    "rating": 171.467,
    "reviews": 0,
    "property_type": "Unknown",
    "city": "Ust-Kamenogorsk",
    "country": "Kazakhstan",
    "currency": "USD",
    "scraped_at": "2025-12-04T00:23:16.332395",
    "source": "airbnb_kz"
  },
  {
    "id": 9,
    "title": "Apartment in Ust'-Kamenogorsk",
    "price": 100977,
    "rating": 100.977,
    "reviews": 3,
    "property_type": "Apartment",
    "city": "Ust-Kamenogorsk",
    "country": "Kazakhstan",
    "currency": "USD",
    "scraped_at": "2025-12-04T00:23:16.363800",
    "source": "airbnb_kz"
  },
  {
    "id": 10,
    "title": "Apartment in Ust'-Kamenogorsk",
    "price": 64929,
    "rating": 64.929,
    "reviews": 0,
    "property_type": "Apartment",
    "city": "Ust-Kamenogorsk",
    "country": "Kazakhstan",
    "currency": "USD",
    "scraped_at": "2025-12-04T00:23:16.383330",
    "source": "airbnb_kz"
  },
  {
    "id": 11,
    "title": "Apartment in Ust'-Kamenogorsk",
    "price": 118678,
    "rating": 118.678,
    "reviews": 0,
    "property_type": "Apartment",
    "city": "Ust-Kamenogorsk",
    "country": "Kazakhstan",
    "currency": "USD",
    "scraped_at": "2025-12-04T00:23:16.401806",
    "source": "airbnb_kz"
  },
  {
    "id": 12,
    "title": "Apartment in Ust'-Kamenogorsk",
    "price": 98416,
    "rating": 98.416,
    "reviews": 0,
    "property_type": "Apartment",
    "city": "Ust-Kamenogorsk",
    "country": "Kazakhstan",
    "currency": "USD",
    "scraped_at": "2025-12-04T00:23:16.420673",
    "source": "airbnb_kz"
  },
  {
    "id": 13,
    "title": "Apartment in Ust'-Kamenogorsk",
    "price": 92656,
    "rating": 92.656,
    "reviews": 0,
    "property_type": "Apartment",
    "city": "Ust-Kamenogorsk",
    "country": "Kazakhstan",
    "currency": "USD",
    "scraped_at": "2025-12-04T00:23:16.439048",
    "source": "airbnb_kz"
  },
  {
    "id": 14,
    "title": "Apartment in Ust'-Kamenogorsk",
    "price": 159202,
    "rating": 159.202,
    "reviews": 0,
    "property_type": "Apartment",
    "city": "Ust-Kamenogorsk",
    "country": "Kazakhstan",
    "currency": "USD",
    "scraped_at": "2025-12-04T00:23:16.461165",
    "source": "airbnb_kz"
  },
  {
    "id": 15,
    "title": "Apartment in Ust'-Kamenogorsk",
    "price": 92627,
    "rating": 92.627,
    "reviews": 4,
    "property_type": "Apartment",
    "city": "Ust-Kamenogorsk",
    "country": "Kazakhstan",
    "currency": "USD",
    "scraped_at": "2025-12-04T00:23:16.488142",
    "source": "airbnb_kz"
  },
  {
    "id": 16,
    "title": "Apartment in Ust'-Kamenogorsk",
    "price": 121573,
    "rating": 121.573,
    "reviews": 0,
    "property_type": "Apartment",
    "city": "Ust-Kamenogorsk",
    "country": "Kazakhstan",
    "currency": "USD",
    "scraped_at": "2025-12-04T00:23:16.515076",
    "source": "airbnb_kz"
  },
  {
    "id": 17,
    "title": "Room in Ust'-Kamenogorsk",
    "price": 31841,
    "rating": 31.841,
    "reviews": 0,
    "property_type": "Room",
    "city": "Ust-Kamenogorsk",
    "country": "Kazakhstan",
    "currency": "USD",
    "scraped_at": "2025-12-04T00:23:16.542010",
    "source": "airbnb_kz"
  },
  {
    "id": 18,
    "title": "Apartment in Ust'-Kamenogorsk",
    "price": 86838,
    "rating": 86.838,
    "reviews": 3,
    "property_type": "Apartment",
    "city": "Ust-Kamenogorsk",
    "country": "Kazakhstan",
    "currency": "USD",
    "scraped_at": "2025-12-04T00:23:16.567637",
    "source": "airbnb_kz"
  },
  {
    "id": 1,
    "title": "Apartment in Semey",
    "price": 94287,
    "rating": 94.287,
    "reviews": 0,
    "property_type": "Apartment",
    "city": "Semey",
    "country": "Kazakhstan",
    "currency": "USD",
    "scraped_at": "2025-12-04T00:23:53.353107",
    "source": "airbnb_kz"
  },
  {
    "id": 1,
    "title": "Superhost",
    "price": 144729,
    "rating": 144.729,
    "reviews": 0,
    "property_type": "Unknown",
    "city": "Kostanay",
    "country": "Kazakhstan",
    "currency": "USD",
    "scraped_at": "2025-12-04T00:24:26.232794",
    "source": "airbnb_kz"
  },
  {
    "id": 1,
    "title": "Apartment in Kyzylorda",
    "price": 115784,
    "rating": 115.784,
    "reviews": 4,
    "property_type": "Apartment",
    "city": "Kyzylorda",
    "country": "Kazakhstan",
    "currency": "USD",
    "scraped_at": "2025-12-04T00:24:59.668542",
    "source": "airbnb_kz"
  },
  {
    "id": 2,
    "title": "Apartment in Kyzylorda",
    "price": 228672,
    "rating": 228.672,
    "reviews": 0,
    "property_type": "Apartment",
    "city": "Kyzylorda",
    "country": "Kazakhstan",
    "currency": "USD",
    "scraped_at": "2025-12-04T00:24:59.691543",
    "source": "airbnb_kz"
  },
  {
    "id": 3,
    "title": "Apartment in Kyzylorda",
    "price": 115784,
    "rating": 115.784,
    "reviews": 0,
    "property_type": "Apartment",
    "city": "Kyzylorda",
    "country": "Kazakhstan",
    "currency": "USD",
    "scraped_at": "2025-12-04T00:24:59.710967",
    "source": "airbnb_kz"
  },
  {
    "id": 4,
    "title": "Apartment in Kyzylorda",
    "price": 222883,
    "rating": 222.883,
    "reviews": 0,
    "property_type": "Apartment",
    "city": "Kyzylorda",
    "country": "Kazakhstan",
    "currency": "USD",
    "scraped_at": "2025-12-04T00:24:59.765243",
    "source": "airbnb_kz"
  },
  {
    "id": 5,
    "title": "Apartment in Kyzylorda",
    "price": 107100,
    "rating": 107.1,
    "reviews": 0,
    "property_type": "Apartment",
    "city": "Kyzylorda",
    "country": "Kazakhstan",
    "currency": "USD",
    "scraped_at": "2025-12-04T00:24:59.788050",
    "source": "airbnb_kz"
  },
  {
    "id": 6,
    "title": "Apartment in Kyzylorda",
    "price": 109994,
    "rating": 109.994,
    "reviews": 0,
    "property_type": "Apartment",
    "city": "Kyzylorda",
    "country": "Kazakhstan",
    "currency": "USD",
    "scraped_at": "2025-12-04T00:24:59.808263",
    "source": "airbnb_kz"
  },
  {
    "id": 7,
    "title": "Hotel in Kyzylorda",
    "price": 172766,
    "rating": 172.766,
    "reviews": 0,
    "property_type": "Hotel",
    "city": "Kyzylorda",
    "country": "Kazakhstan",
    "currency": "USD",
    "scraped_at": "2025-12-04T00:24:59.827037",
    "source": "airbnb_kz"
  },
  {
    "id": 8,
    "title": "Hotel in Kyzylorda",
    "price": 257454,
    "rating": 257.454,
    "reviews": 0,
    "property_type": "Hotel",
    "city": "Kyzylorda",
    "country": "Kazakhstan",
    "currency": "USD",
    "scraped_at": "2025-12-04T00:24:59.845612",
    "source": "airbnb_kz"
  },
  {
    "id": 9,
    "title": "Apartment in Kyzylorda",
    "price": 104205,
    "rating": 104.205,
    "reviews": 6,
    "property_type": "Apartment",
    "city": "Kyzylorda",
    "country": "Kazakhstan",
    "currency": "USD",
    "scraped_at": "2025-12-04T00:24:59.864558",
    "source": "airbnb_kz"
  },
  {
    "id": 10,
    "title": "Place to stay in Kyzylorda",
    "price": 87996,
    "rating": 87.996,
    "reviews": 0,
    "property_type": "Unknown",
    "city": "Kyzylorda",
    "country": "Kazakhstan",
    "currency": "USD",
    "scraped_at": "2025-12-04T00:24:59.888590",
    "source": "airbnb_kz"
  },
  {
    "id": 11,
    "title": "Apartment in Kyzylorda",
    "price": 155263,
    "rating": 155.263,
    "reviews": 0,
    "property_type": "Apartment",
    "city": "Kyzylorda",
    "country": "Kazakhstan",
    "currency": "USD",
    "scraped_at": "2025-12-04T00:24:59.914533",
    "source": "airbnb_kz"
  },
  {
    "id": 12,
    "title": "Condo in Kyzylorda",
    "price": 109994,
    "rating": 109.994,
    "reviews": 0,
    "property_type": "Unknown",
    "city": "Kyzylorda",
    "country": "Kazakhstan",
    "currency": "USD",
    "scraped_at": "2025-12-04T00:24:59.938462",
    "source": "airbnb_kz"
  },
  {
    "id": 13,
    "title": "Apartment in Kyzylorda",
    "price": 126204,
    "rating": 126.204,
    "reviews": 0,
    "property_type": "Apartment",
    "city": "Kyzylorda",
    "country": "Kazakhstan",
    "currency": "USD",
    "scraped_at": "2025-12-04T00:24:59.962007",
    "source": "airbnb_kz"
  },
  {
    "id": 14,
    "title": "Apartment in Kyzylorda",
    "price": 158086,
    "rating": 158.086,
    "reviews": 0,
    "property_type": "Apartment",
    "city": "Kyzylorda",
    "country": "Kazakhstan",
    "currency": "USD",
    "scraped_at": "2025-12-04T00:24:59.986491",
    "source": "airbnb_kz"
  },
  {
    "id": 15,
    "title": "Condo in Kyzylorda",
    "price": 86838,
    "rating": 86.838,
    "reviews": 0,
    "property_type": "Unknown",
    "city": "Kyzylorda",
    "country": "Kazakhstan",
    "currency": "USD",
    "scraped_at": "2025-12-04T00:25:00.010575",
    "source": "airbnb_kz"
  },
  {
    "id": 16,
    "title": "Condo in Kyzylorda",
    "price": 86838,
    "rating": 86.838,
    "reviews": 0,
    "property_type": "Unknown",
    "city": "Kyzylorda",
    "country": "Kazakhstan",
    "currency": "USD",
    "scraped_at": "2025-12-04T00:25:00.033826",
    "source": "airbnb_kz"
  },
  {
    "id": 17,
    "title": "Apartment in Kyzylorda",
    "price": 102360,
    "rating": 102.36,
    "reviews": 0,
    "property_type": "Apartment",
    "city": "Kyzylorda",
    "country": "Kazakhstan",
    "currency": "USD",
    "scraped_at": "2025-12-04T00:25:00.055526",
    "source": "airbnb_kz"
  },
  {
    "id": 18,
    "title": "Hotel in Kyzylorda",
    "price": 225837,
    "rating": 225.837,
    "reviews": 0,
    "property_type": "Hotel",
    "city": "Kyzylorda",
    "country": "Kazakhstan",
    "currency": "USD",
    "scraped_at": "2025-12-04T00:25:00.078984",
    "source": "airbnb_kz"
  },
  {
    "id": 1,
    "title": "Guest favorite",
    "price": 124467,
    "rating": 124.467,
    "reviews": 10,
    "property_type": "Unknown",
    "city": "Uralsk",
    "country": "Kazakhstan",
    "currency": "USD",
    "scraped_at": "2025-12-04T00:25:37.183575",
    "source": "airbnb_kz"
  },
  {
    "id": 1,
    "title": "Apartment in Petropavl",
    "price": 89732,
    "rating": 89.732,
    "reviews": 0,
    "property_type": "Apartment",
    "city": "Petropavl",
    "country": "Kazakhstan",
    "currency": "USD",
    "scraped_at": "2025-12-04T00:26:11.240005",
    "source": "airbnb_kz"
  },
  {
    "id": 1,
    "title": "Apartment in Atyrau",
    "price": 172481,
    "rating": 172.481,
    "reviews": 18,
    "property_type": "Apartment",
    "city": "Atyrau",
    "country": "Kazakhstan",
    "currency": "USD",
    "scraped_at": "2025-12-04T00:26:45.010599",
    "source": "airbnb_kz"
  },
  {
    "id": 2,
    "title": "Apartment in Atyrau",
    "price": 95522,
    "rating": 43.6,
    "reviews": 0,
    "property_type": "Apartment",
    "city": "Atyrau",
    "country": "Kazakhstan",
    "currency": "USD",
    "scraped_at": "2025-12-04T00:26:45.027284",
    "source": "airbnb_kz"
  },
  {
    "id": 3,
    "title": "Apartment in Atyrau",
    "price": 92627,
    "rating": 92.627,
    "reviews": 0,
    "property_type": "Apartment",
    "city": "Atyrau",
    "country": "Kazakhstan",
    "currency": "USD",
    "scraped_at": "2025-12-04T00:26:45.044243",
    "source": "airbnb_kz"
  },
  {
    "id": 4,
    "title": "Superhost",
    "price": 130257,
    "rating": 130.257,
    "reviews": 4,
    "property_type": "Unknown",
    "city": "Atyrau",
    "country": "Kazakhstan",
    "currency": "USD",
    "scraped_at": "2025-12-04T00:26:45.074385",
    "source": "airbnb_kz"
  },
  {
    "id": 5,
    "title": "Apartment in Atyrau",
    "price": 142044,
    "rating": 142.044,
    "reviews": 0,
    "property_type": "Apartment",
    "city": "Atyrau",
    "country": "Kazakhstan",
    "currency": "USD",
    "scraped_at": "2025-12-04T00:26:45.093736",
    "source": "airbnb_kz"
  },
  {
    "id": 6,
    "title": "Apartment in Atyrau",
    "price": 81049,
    "rating": 81.049,
    "reviews": 0,
    "property_type": "Apartment",
    "city": "Atyrau",
    "country": "Kazakhstan",
    "currency": "USD",
    "scraped_at": "2025-12-04T00:26:45.112952",
    "source": "airbnb_kz"
  },
  {
    "id": 7,
    "title": "Apartment in Atyrau",
    "price": 137204,
    "rating": 137.204,
    "reviews": 0,
    "property_type": "Apartment",
    "city": "Atyrau",
    "country": "Kazakhstan",
    "currency": "USD",
    "scraped_at": "2025-12-04T00:26:45.138356",
    "source": "airbnb_kz"
  },
  {
    "id": 8,
    "title": "Guest favorite",
    "price": 130257,
    "rating": 130.257,
    "reviews": 6,
    "property_type": "Unknown",
    "city": "Atyrau",
    "country": "Kazakhstan",
    "currency": "USD",
    "scraped_at": "2025-12-04T00:26:45.168664",
    "source": "airbnb_kz"
  },
  {
    "id": 9,
    "title": "Apartment in Atyrau",
    "price": 109994,
    "rating": 109.994,
    "reviews": 0,
    "property_type": "Apartment",
    "city": "Atyrau",
    "country": "Kazakhstan",
    "currency": "USD",
    "scraped_at": "2025-12-04T00:26:45.185098",
    "source": "airbnb_kz"
  },
  {
    "id": 10,
    "title": "Apartment in Atyrau",
    "price": 79043,
    "rating": 79.043,
    "reviews": 0,
    "property_type": "Apartment",
    "city": "Atyrau",
    "country": "Kazakhstan",
    "currency": "USD",
    "scraped_at": "2025-12-04T00:26:45.202329",
    "source": "airbnb_kz"
  },
  {
    "id": 11,
    "title": "Boutique hotel in Atyrau",
    "price": 38105,
    "rating": 38.105,
    "reviews": 0,
    "property_type": "Hotel",
    "city": "Atyrau",
    "country": "Kazakhstan",
    "currency": "USD",
    "scraped_at": "2025-12-04T00:26:45.218672",
    "source": "airbnb_kz"
  },
  {
    "id": 12,
    "title": "Superhost",
    "price": 191043,
    "rating": 191.043,
    "reviews": 0,
    "property_type": "Unknown",
    "city": "Atyrau",
    "country": "Kazakhstan",
    "currency": "USD",
    "scraped_at": "2025-12-04T00:26:45.235440",
    "source": "airbnb_kz"
  },
  {
    "id": 13,
    "title": "Apartment in Atyrau",
    "price": 136971,
    "rating": 136.971,
    "reviews": 3,
    "property_type": "Apartment",
    "city": "Atyrau",
    "country": "Kazakhstan",
    "currency": "USD",
    "scraped_at": "2025-12-04T00:26:45.252645",
    "source": "airbnb_kz"
  },
  {
    "id": 14,
    "title": "Guest favorite",
    "price": 100153,
    "rating": 100.153,
    "reviews": 15,
    "property_type": "Unknown",
    "city": "Atyrau",
    "country": "Kazakhstan",
    "currency": "USD",
    "scraped_at": "2025-12-04T00:26:45.270626",
    "source": "airbnb_kz"
  },
  {
    "id": 15,
    "title": "Superhost",
    "price": 153413,
    "rating": 153.413,
    "reviews": 0,
    "property_type": "Unknown",
    "city": "Atyrau",
    "country": "Kazakhstan",
    "currency": "USD",
    "scraped_at": "2025-12-04T00:26:45.287436",
    "source": "airbnb_kz"
  },
  {
    "id": 16,
    "title": "Apartment in Atyrau",
    "price": 126825,
    "rating": 126.825,
    "reviews": 4,
    "property_type": "Apartment",
    "city": "Atyrau",
    "country": "Kazakhstan",
    "currency": "USD",
    "scraped_at": "2025-12-04T00:26:45.304682",
    "source": "airbnb_kz"
  },
  {
    "id": 17,
    "title": "Apartment in Atyrau",
    "price": 188148,
    "rating": 188.148,
    "reviews": 0,
    "property_type": "Apartment",
    "city": "Atyrau",
    "country": "Kazakhstan",
    "currency": "USD",
    "scraped_at": "2025-12-04T00:26:45.321169",
    "source": "airbnb_kz"
  },
  {
    "id": 18,
    "title": "Apartment in Atyrau",
    "price": 97583,
    "rating": 97.583,
    "reviews": 0,
    "property_type": "Apartment",
    "city": "Atyrau",
    "country": "Kazakhstan",
    "currency": "USD",
    "scraped_at": "2025-12-04T00:26:45.338366",
    "source": "airbnb_kz"
  },
  {
    "id": 1,
    "title": "Apartment in Turkistan",
    "price": 133962,
    "rating": 133.962,
    "reviews": 0,
    "property_type": "Apartment",
    "city": "Turkistan",
    "country": "Kazakhstan",
    "currency": "USD",
    "scraped_at": "2025-12-04T00:27:15.286557",
    "source": "airbnb_kz"
  },
  {
    "id": 2,
    "title": "Apartment in Turkistan",
    "price": 173675,
    "rating": 173.675,
    "reviews": 0,
    "property_type": "Apartment",
    "city": "Turkistan",
    "country": "Kazakhstan",
    "currency": "USD",
    "scraped_at": "2025-12-04T00:27:15.304162",
    "source": "airbnb_kz"
  },
  {
    "id": 3,
    "title": "Top guest favorite",
    "price": 31841,
    "rating": 31.841,
    "reviews": 6,
    "property_type": "Unknown",
    "city": "Turkistan",
    "country": "Kazakhstan",
    "currency": "USD",
    "scraped_at": "2025-12-04T00:27:15.321613",
    "source": "airbnb_kz"
  },
  {
    "id": 4,
    "title": "Rooms in Turkistan",
    "price": 42345,
    "rating": 42.345,
    "reviews": 0,
    "property_type": "Room",
    "city": "Turkistan",
    "country": "Kazakhstan",
    "currency": "USD",
    "scraped_at": "2025-12-04T00:27:15.340813",
    "source": "airbnb_kz"
  },
  {
    "id": 5,
    "title": "Apartment in Turkistan",
    "price": 78154,
    "rating": 78.154,
    "reviews": 0,
    "property_type": "Apartment",
    "city": "Turkistan",
    "country": "Kazakhstan",
    "currency": "USD",
    "scraped_at": "2025-12-04T00:27:15.357005",
    "source": "airbnb_kz"
  },
  {
    "id": 6,
    "title": "Apartment in Turkistan",
    "price": 99933,
    "rating": 99.933,
    "reviews": 0,
    "property_type": "Apartment",
    "city": "Turkistan",
    "country": "Kazakhstan",
    "currency": "USD",
    "scraped_at": "2025-12-04T00:27:15.374115",
    "source": "airbnb_kz"
  },
  {
    "id": 7,
    "title": "Apartment in Turkistan",
    "price": 156308,
    "rating": 156.308,
    "reviews": 0,
    "property_type": "Apartment",
    "city": "Turkistan",
    "country": "Kazakhstan",
    "currency": "USD",
    "scraped_at": "2025-12-04T00:27:15.390556",
    "source": "airbnb_kz"
  },
  {
    "id": 8,
    "title": "Apartment in Turkistan",
    "price": 91973,
    "rating": 91.973,
    "reviews": 0,
    "property_type": "Apartment",
    "city": "Turkistan",
    "country": "Kazakhstan",
    "currency": "USD",
    "scraped_at": "2025-12-04T00:27:15.418144",
    "source": "airbnb_kz"
  },
  {
    "id": 9,
    "title": "Room in Turkistan",
    "price": 124467,
    "rating": 124.467,
    "reviews": 0,
    "property_type": "Room",
    "city": "Turkistan",
    "country": "Kazakhstan",
    "currency": "USD",
    "scraped_at": "2025-12-04T00:27:15.438540",
    "source": "airbnb_kz"
  },
  {
    "id": 10,
    "title": "Apartment in Turkistan",
    "price": 130257,
    "rating": 130.257,
    "reviews": 0,
    "property_type": "Apartment",
    "city": "Turkistan",
    "country": "Kazakhstan",
    "currency": "USD",
    "scraped_at": "2025-12-04T00:27:15.456493",
    "source": "airbnb_kz"
  },
  {
    "id": 11,
    "title": "Apartment in Turkistan",
    "price": 144580,
    "rating": 144.58,
    "reviews": 3,
    "property_type": "Apartment",
    "city": "Turkistan",
    "country": "Kazakhstan",
    "currency": "USD",
    "scraped_at": "2025-12-04T00:27:15.482154",
    "source": "airbnb_kz"
  },
  {
    "id": 12,
    "title": "Apartment in Turkistan",
    "price": 164872,
    "rating": 164.872,
    "reviews": 4,
    "property_type": "Apartment",
    "city": "Turkistan",
    "country": "Kazakhstan",
    "currency": "USD",
    "scraped_at": "2025-12-04T00:27:15.507192",
    "source": "airbnb_kz"
  },
  {
    "id": 13,
    "title": "Home in Turkistan",
    "price": 72365,
    "rating": 72.365,
    "reviews": 4,
    "property_type": "House",
    "city": "Turkistan",
    "country": "Kazakhstan",
    "currency": "USD",
    "scraped_at": "2025-12-04T00:27:15.523828",
    "source": "airbnb_kz"
  },
  {
    "id": 14,
    "title": "Rooms in Turkistan",
    "price": 43419,
    "rating": 43.419,
    "reviews": 15,
    "property_type": "Room",
    "city": "Turkistan",
    "country": "Kazakhstan",
    "currency": "USD",
    "scraped_at": "2025-12-04T00:27:15.543038",
    "source": "airbnb_kz"
  },
  {
    "id": 15,
    "title": "Apartment in Turkistan",
    "price": 139507,
    "rating": 139.507,
    "reviews": 0,
    "property_type": "Apartment",
    "city": "Turkistan",
    "country": "Kazakhstan",
    "currency": "USD",
    "scraped_at": "2025-12-04T00:27:15.559016",
    "source": "airbnb_kz"
  },
  {
    "id": 16,
    "title": "Hotel in Turkistan",
    "price": 98804,
    "rating": 98.804,
    "reviews": 0,
    "property_type": "Hotel",
    "city": "Turkistan",
    "country": "Kazakhstan",
    "currency": "USD",
    "scraped_at": "2025-12-04T00:27:15.575682",
    "source": "airbnb_kz"
  },
  {
    "id": 17,
    "title": "Apartment in Turkistan",
    "price": 144729,
    "rating": 144.729,
    "reviews": 5,
    "property_type": "Apartment",
    "city": "Turkistan",
    "country": "Kazakhstan",
    "currency": "USD",
    "scraped_at": "2025-12-04T00:27:15.592437",
    "source": "airbnb_kz"
  },
  {
    "id": 18,
    "title": "Apartment in Turkistan",
    "price": 141148,
    "rating": 141.148,
    "reviews": 0,
    "property_type": "Apartment",
    "city": "Turkistan",
    "country": "Kazakhstan",
    "currency": "USD",
    "scraped_at": "2025-12-04T00:27:15.608937",
    "source": "airbnb_kz"
  },
  {
    "id": 1,
    "title": "Guest favorite",
    "price": 91469,
    "rating": 91.469,
    "reviews": 9,
    "property_type": "Unknown",
    "city": "Kokshetau",
    "country": "Kazakhstan",
    "currency": "USD",
    "scraped_at": "2025-12-04T00:27:50.135763",
    "source": "airbnb_kz"
  },
  {
    "id": 2,
    "title": "Apartment in Kokshetau",
    "price": 104784,
    "rating": 104.784,
    "reviews": 3,
    "property_type": "Apartment",
    "city": "Kokshetau",
    "country": "Kazakhstan",
    "currency": "USD",
    "scraped_at": "2025-12-04T00:27:50.157028",
    "source": "airbnb_kz"
  },
  {
    "id": 3,
    "title": "Apartment in Kokshetau",
    "price": 64839,
    "rating": 64.839,
    "reviews": 3,
    "property_type": "Apartment",
    "city": "Kokshetau",
    "country": "Kazakhstan",
    "currency": "USD",
    "scraped_at": "2025-12-04T00:27:50.176669",
    "source": "airbnb_kz"
  },
  {
    "id": 4,
    "title": "Apartment in Kokshetau",
    "price": 89154,
    "rating": 89.154,
    "reviews": 0,
    "property_type": "Apartment",
    "city": "Kokshetau",
    "country": "Kazakhstan",
    "currency": "USD",
    "scraped_at": "2025-12-04T00:27:50.202055",
    "source": "airbnb_kz"
  },
  {
    "id": 5,
    "title": "Apartment in Kokshetau",
    "price": 92164,
    "rating": 92.164,
    "reviews": 0,
    "property_type": "Apartment",
    "city": "Kokshetau",
    "country": "Kazakhstan",
    "currency": "USD",
    "scraped_at": "2025-12-04T00:27:50.223910",
    "source": "airbnb_kz"
  },
  {
    "id": 6,
    "title": "Apartment in Kokshetau",
    "price": 81049,
    "rating": 81.049,
    "reviews": 0,
    "property_type": "Apartment",
    "city": "Kokshetau",
    "country": "Kazakhstan",
    "currency": "USD",
    "scraped_at": "2025-12-04T00:27:50.239460",
    "source": "airbnb_kz"
  },
  {
    "id": 7,
    "title": "Apartment in Kokshetau",
    "price": 140677,
    "rating": 140.677,
    "reviews": 0,
    "property_type": "Apartment",
    "city": "Kokshetau",
    "country": "Kazakhstan",
    "currency": "USD",
    "scraped_at": "2025-12-04T00:27:50.255028",
    "source": "airbnb_kz"
  },
  {
    "id": 8,
    "title": "Apartment in Kokshetau",
    "price": 92627,
    "rating": 92.627,
    "reviews": 5,
    "property_type": "Apartment",
    "city": "Kokshetau",
    "country": "Kazakhstan",
    "currency": "USD",
    "scraped_at": "2025-12-04T00:27:50.271637",
    "source": "airbnb_kz"
  },
  {
    "id": 9,
    "title": "Apartment in Kokshetau",
    "price": 101062,
    "rating": 101.062,
    "reviews": 0,
    "property_type": "Apartment",
    "city": "Kokshetau",
    "country": "Kazakhstan",
    "currency": "USD",
    "scraped_at": "2025-12-04T00:27:50.287935",
    "source": "airbnb_kz"
  },
  {
    "id": 10,
    "title": "Apartment in Kokshetau",
    "price": 98804,
    "rating": 98.804,
    "reviews": 0,
    "property_type": "Apartment",
    "city": "Kokshetau",
    "country": "Kazakhstan",
    "currency": "USD",
    "scraped_at": "2025-12-04T00:27:50.304298",
    "source": "airbnb_kz"
  },
  {
    "id": 11,
    "title": "Apartment in Kokshetau",
    "price": 94943,
    "rating": 94.943,
    "reviews": 0,
    "property_type": "Apartment",
    "city": "Kokshetau",
    "country": "Kazakhstan",
    "currency": "USD",
    "scraped_at": "2025-12-04T00:27:50.322779",
    "source": "airbnb_kz"
  },
  {
    "id": 12,
    "title": "Apartment in Kokshetau",
    "price": 98239,
    "rating": 98.239,
    "reviews": 0,
    "property_type": "Apartment",
    "city": "Kokshetau",
    "country": "Kazakhstan",
    "currency": "USD",
    "scraped_at": "2025-12-04T00:27:50.339758",
    "source": "airbnb_kz"
  },
  {
    "id": 13,
    "title": "Apartment in Kokshetau",
    "price": 115784,
    "rating": 115.784,
    "reviews": 0,
    "property_type": "Apartment",
    "city": "Kokshetau",
    "country": "Kazakhstan",
    "currency": "USD",
    "scraped_at": "2025-12-04T00:27:50.356904",
    "source": "airbnb_kz"
  },
  {
    "id": 14,
    "title": "Apartment in Kokshetau",
    "price": 115784,
    "rating": 115.784,
    "reviews": 0,
    "property_type": "Apartment",
    "city": "Kokshetau",
    "country": "Kazakhstan",
    "currency": "USD",
    "scraped_at": "2025-12-04T00:27:50.373266",
    "source": "airbnb_kz"
  },
  {
    "id": 15,
    "title": "Apartment in Kokshetau",
    "price": 52103,
    "rating": 52.103,
    "reviews": 0,
    "property_type": "Apartment",
    "city": "Kokshetau",
    "country": "Kazakhstan",
    "currency": "USD",
    "scraped_at": "2025-12-04T00:27:50.389276",
    "source": "airbnb_kz"
  },
  {
    "id": 16,
    "title": "Apartment in Kokshetau",
    "price": 144729,
    "rating": 144.729,
    "reviews": 0,
    "property_type": "Apartment",
    "city": "Kokshetau",
    "country": "Kazakhstan",
    "currency": "USD",
    "scraped_at": "2025-12-04T00:27:50.406955",
    "source": "airbnb_kz"
  },
  {
    "id": 17,
    "title": "Apartment in Kokshetau",
    "price": 104450,
    "rating": 104.45,
    "reviews": 0,
    "property_type": "Apartment",
    "city": "Kokshetau",
    "country": "Kazakhstan",
    "currency": "USD",
    "scraped_at": "2025-12-04T00:27:50.423622",
    "source": "airbnb_kz"
  },
  {
    "id": 18,
    "title": "Apartment in Kokshetau",
    "price": 112919,
    "rating": 112.919,
    "reviews": 0,
    "property_type": "Apartment",
    "city": "Kokshetau",
    "country": "Kazakhstan",
    "currency": "USD",
    "scraped_at": "2025-12-04T00:27:50.440162",
    "source": "airbnb_kz"
  },
  {
    "id": 1,
    "title": "Apartment in Balkhash",
    "price": 198737,
    "rating": 198.737,
    "reviews": 0,
    "property_type": "Apartment",
    "city": "Zhezkazgan",
    "country": "Kazakhstan",
    "currency": "USD",
    "scraped_at": "2025-12-04T00:59:42.203859",
    "source": "airbnb_kz"
  },
  {
    "id": 1,
    "title": "Guest favorite",
    "price": 183896,
    "rating": 183.896,
    "reviews": 39,
    "property_type": "Unknown",
    "city": "Алматы",
    "country": "Kazakhstan",
    "currency": "USD",
    "scraped_at": "2025-12-04T01:00:12.411197",
    "source": "airbnb_kz"
  },
  {
    "id": 1,
    "title": "Guest favorite",
    "price": 101311,
    "rating": 101.311,
    "reviews": 27,
    "property_type": "Unknown",
    "city": "Шымкент",
    "country": "Kazakhstan",
    "currency": "USD",
    "scraped_at": "2025-12-04T01:31:51.251766",
    "source": "airbnb_kz"
  }
]